mylib1/__init__.py
mylib_040/__init__.py
mylib_040-0.1.dist-info/LICENSE.txt
mylib_040-0.1.dist-info/METADATA
mylib_040-0.1.dist-info/WHEEL
mylib_040-0.1.dist-info/top_level.txt
mylib_040-0.1.dist-info/RECORD
