Metadata-Version: 2.1
Name: mylib-040
Version: 0.1
Summary: for calculating square
Author: Shreyas
Author-email: srdhobekar7jun@gmail.com
Classifier: Programming Language :: Python :: 3
Classifier: License :: OSI Approved :: MIT License
Classifier: Operating System :: OS Independent
License-File: LICENSE.txt
